server.py
config/__init__.py
robot_specifications/YOUR_ROBOT_NAME.yaml
robot_specifications/__init__.py
robot_specifications/local_rosbridge.yaml
robot_specifications/unitree_go2.yaml
ros_mcp-2.2.1.data/data/server.json
ros_mcp-2.2.1.dist-info/licenses/LICENSE
utils/__init__.py
utils/config_utils.py
utils/network_utils.py
utils/websocket_manager.py
ros_mcp-2.2.1.dist-info/METADATA
ros_mcp-2.2.1.dist-info/WHEEL
ros_mcp-2.2.1.dist-info/entry_points.txt
ros_mcp-2.2.1.dist-info/top_level.txt
ros_mcp-2.2.1.dist-info/RECORD
