Metadata-Version: 2.4
Name: ros-mcp
Version: 2.2.1
Summary: Connect AI Language Models with Robots on ROS using MCP
Author: Rohit John Varghese, Jungsoo Lee, Youngmok Yun, Stefano Dalla Gasperina
License-Expression: Apache-2.0
Requires-Python: >=3.10
License-File: LICENSE
Requires-Dist: fastmcp>=2.11.3
Requires-Dist: jsonschema>=4.25.1
Requires-Dist: mcp[cli]>=1.13.0
Requires-Dist: opencv-python>=4.11.0.86
Requires-Dist: pillow>=11.3.0
Requires-Dist: websocket-client>=1.8.0
Provides-Extra: dev
Requires-Dist: ruff; extra == "dev"
Requires-Dist: pytest; extra == "dev"
Dynamic: license-file
